{"name":"AngularJS","postlist":[{"title":"使用 AngularJS v1.5+ 建立 component-based 應用程式","slug":"component-based-application-using-angularjs-v1.5+","date":"2016-12-23T18:02:30.000Z","updated":"2021-09-05T09:19:12.875Z","comments":true,"path":"api/articles/component-based-application-using-angularjs-v1.5+.json","excerpt":null,"keywords":null,"cover":"/2016/12/24/component-based-application-using-angularjs-v1.5+/cover.jpg","content":null,"raw":null,"categories":[{"name":"技術分享","path":"api/categories/技術分享.json"}],"tags":[{"name":"AngularJS","path":"api/tags/AngularJS.json"},{"name":"前端工程","path":"api/tags/前端工程.json"}]}]}